snappi/__init__.py
snappi/otg_pb2.py
snappi/otg_pb2_grpc.py
snappi/snappi.py
snappi-1.44.0.dist-info/licenses/LICENSE
snappi-1.44.0.dist-info/METADATA
snappi-1.44.0.dist-info/WHEEL
snappi-1.44.0.dist-info/top_level.txt
snappi-1.44.0.dist-info/RECORD
