Metadata-Version: 2.4
Name: snappi
Version: 1.44.0
Summary: The Snappi Open Traffic Generator Python Package
Author-email: Keysight Technologies <andy.balogh@keysight.com>
License-Expression: MIT
Project-URL: Repository, https://github.com/open-traffic-generator/snappi
Keywords: snappi,testing,open traffic generator,automation
Classifier: Development Status :: 5 - Production/Stable
Classifier: Intended Audience :: Developers
Classifier: Topic :: Software Development :: Testing :: Traffic Generation
Classifier: Programming Language :: Python :: 3
Classifier: Programming Language :: Python :: 3.8
Classifier: Programming Language :: Python :: 3.9
Classifier: Programming Language :: Python :: 3.10
Classifier: Programming Language :: Python :: 3.11
Classifier: Programming Language :: Python :: 3.12
Requires-Python: <4,>=3.8
License-File: LICENSE
Requires-Dist: PyYAML
Requires-Dist: grpcio-tools~=1.70.0
Requires-Dist: grpcio~=1.70.0
Requires-Dist: protobuf~=5.29.5
Requires-Dist: requests
Requires-Dist: semantic_version
Requires-Dist: urllib3
Provides-Extra: ixnetwork
Requires-Dist: snappi_ixnetwork==1.42.1; extra == "ixnetwork"
Provides-Extra: trex
Requires-Dist: snappi_trex; extra == "trex"
Provides-Extra: testing
Requires-Dist: pytest; extra == "testing"
Requires-Dist: flask; extra == "testing"
Provides-Extra: telemetry
Requires-Dist: opentelemetry-api==1.17.0; python_version >= "3.7" and extra == "telemetry"
Requires-Dist: opentelemetry-sdk; python_version >= "3.7" and extra == "telemetry"
Requires-Dist: opentelemetry-exporter-otlp-proto-http; python_version >= "3.7" and extra == "telemetry"
Requires-Dist: opentelemetry-exporter-otlp-proto-grpc; python_version >= "3.7" and extra == "telemetry"
Requires-Dist: opentelemetry-instrumentation-grpc; python_version >= "3.7" and extra == "telemetry"
Requires-Dist: opentelemetry-instrumentation-requests; python_version >= "3.7" and extra == "telemetry"
Dynamic: license-file
